bw_graph_tools/__init__.py
bw_graph_tools/errors.py
bw_graph_tools/graph_traversal_utils.py
bw_graph_tools/matrix_tools.py
bw_graph_tools/shortest_path.py
bw_graph_tools/testing.py
bw_graph_tools/graph_traversal/__init__.py
bw_graph_tools/graph_traversal/assumed_diagonal.py
bw_graph_tools/graph_traversal/base.py
bw_graph_tools/graph_traversal/graph_objects.py
bw_graph_tools/graph_traversal/new_node_each_visit.py
bw_graph_tools/graph_traversal/same_node_each_visit.py
bw_graph_tools/graph_traversal/settings.py
bw_graph_tools/graph_traversal/tagged_nodes.py
bw_graph_tools/graph_traversal/utils.py
bw_graph_tools-0.6.dist-info/licenses/LICENSE
bw_graph_tools-0.6.dist-info/METADATA
bw_graph_tools-0.6.dist-info/WHEEL
bw_graph_tools-0.6.dist-info/top_level.txt
bw_graph_tools-0.6.dist-info/RECORD
