Metadata-Version: 2.4
Name: bw_graph_tools
Version: 0.6
Summary: Graph traversal class and utilities
Author-email: Chris Mutel <cmutel@gmail.com>
Maintainer-email: Chris Mutel <cmutel@gmail.com>
Project-URL: source, https://github.com/brightway-lca/bw_graph_tools
Project-URL: homepage, https://github.com/brightway-lca/bw_graph_tools
Project-URL: tracker, https://github.com/brightway-lca/bw_graph_tools/issues
Classifier: Development Status :: 5 - Production/Stable
Classifier: Programming Language :: Python
Classifier: Programming Language :: Python :: 3
Classifier: Programming Language :: Python :: 3.9
Classifier: Programming Language :: Python :: 3.10
Classifier: Programming Language :: Python :: 3.11
Classifier: Programming Language :: Python :: 3.12
Classifier: Natural Language :: English
Classifier: Operating System :: OS Independent
Classifier: Topic :: Scientific/Engineering
Requires-Python: >=3.9
License-File: LICENSE
Requires-Dist: bw2calc>=2.0.dev13
Requires-Dist: bw2data>=4.0.dev46
Requires-Dist: bw_processing
Requires-Dist: matrix_utils
Requires-Dist: numpy<3
Requires-Dist: pydantic
Requires-Dist: scipy
Provides-Extra: testing
Requires-Dist: bw_graph_tools; extra == "testing"
Requires-Dist: pytest; extra == "testing"
Requires-Dist: pytest-cov; extra == "testing"
Requires-Dist: python-coveralls; extra == "testing"
Provides-Extra: dev
Requires-Dist: build; extra == "dev"
Requires-Dist: pre-commit; extra == "dev"
Requires-Dist: pylint; extra == "dev"
Requires-Dist: pytest; extra == "dev"
Requires-Dist: pytest-cov; extra == "dev"
Requires-Dist: pytest-randomly; extra == "dev"
Requires-Dist: setuptools; extra == "dev"
Dynamic: license-file
